qutils/__init__.py
qutils/datetime.py
qutils/dlmanager.py
qutils/functions.py
qutils/iotools.py
qutils/misc.py
qutils/models.py
qutils/monkey_patch.py
qutils-0.5.14.dist-info/DESCRIPTION.rst
qutils-0.5.14.dist-info/METADATA
qutils-0.5.14.dist-info/RECORD
qutils-0.5.14.dist-info/WHEEL
qutils-0.5.14.dist-info/metadata.json
qutils-0.5.14.dist-info/top_level.txt
