Metadata-Version: 2.0
Name: qutils
Version: 0.5.14
Summary: utility functions / modules that may be frequently used in simple scripts
Home-page: https://github.com/Raychee/qutils
Author: Raychee Zhang
Author-email: raychee.zhang@gmail.com
License: MIT
Download-URL: https://github.com/Raychee/qutils/tarball/0.5.14
Keywords: utils,common,dlmanager,json,teradata
Platform: UNKNOWN
Classifier: Development Status :: 4 - Beta
Classifier: Intended Audience :: Developers
Classifier: License :: OSI Approved :: MIT License
Classifier: Natural Language :: English
Classifier: Programming Language :: Python :: 3
Classifier: Programming Language :: Python :: 3.5
Classifier: Programming Language :: Python :: 3.6
Classifier: Programming Language :: Python :: 3 :: Only
Classifier: Topic :: Software Development :: Libraries
Classifier: Topic :: Software Development :: Libraries :: Python Modules
Classifier: Topic :: Utilities
Requires-Dist: PyYAML (>=3.12)
Requires-Dist: pandas (>=0.17.0)
Requires-Dist: teradata (>=15.10.0.20)
